aimport/__init__.py
aimport-2.1.0.dist-info/METADATA
aimport-2.1.0.dist-info/WHEEL
aimport-2.1.0.dist-info/top_level.txt
aimport-2.1.0.dist-info/RECORD
