Metadata-Version: 2.4
Name: aimport
Version: 2.1.0
Summary: A minimal library for smart Python imports with automatic path resolution
Author: aimport contributors
License-Expression: MIT
Project-URL: Homepage, https://github.com/ralf12358/aimport
Project-URL: Repository, https://github.com/ralf12358/aimport
Project-URL: Bug Tracker, https://github.com/ralf12358/aimport/issues
Keywords: import,path,module,python,sys.path
Classifier: Development Status :: 4 - Beta
Classifier: Intended Audience :: Developers
Classifier: Programming Language :: Python :: 3
Classifier: Programming Language :: Python :: 3.8
Classifier: Programming Language :: Python :: 3.9
Classifier: Programming Language :: Python :: 3.10
Classifier: Programming Language :: Python :: 3.11
Classifier: Programming Language :: Python :: 3.12
Classifier: Programming Language :: Python :: 3.13
Classifier: Topic :: Software Development :: Libraries :: Python Modules
Classifier: Topic :: System :: Filesystems
Requires-Python: >=3.8
Provides-Extra: dev
Requires-Dist: pytest<8.4.0,>=7.0.0; extra == "dev"
